[
  {
    "id": "nr-mqtt-ota-in",
    "type": "mqtt in",
    "name": "Listen OTA broadcast",
    "topic": "campus/+/+/ota",
    "qos": "1",
    "broker": "nr-broker",
    "x": 120,
    "y": 80,
    "wires": [["nr-verify-hash"]]
  },
  {
    "id": "nr-verify-hash",
    "type": "function",
    "name": "SHA-256 Verify",
    "func": "const crypto = require('crypto');\nlet data;\ntry { data = JSON.parse(msg.payload); } catch(e) {\n  node.warn('Bad JSON from: ' + msg.topic);\n  return null;\n}\nconst parts = msg.topic.split('/');\nconst received = data.hash;\ndelete data.hash;\nconst canonical = JSON.stringify(data, Object.keys(data).sort());\nconst computed = crypto.createHash('sha256').update(canonical).digest('hex');\nif (computed !== received) {\n  msg.payload = { alert:'HASH_MISMATCH', topic: msg.topic, computed, received, ts: Date.now() };\n  node.send([null, msg]);\n  return;\n}\nmsg.validData = data;\nmsg.buildingId = parts[1];\nmsg.floorId = parts[2];\nnode.send([msg, null]);",
    "outputs": 2,
    "x": 340,
    "y": 80,
    "wires": [["nr-build-topics"], ["nr-tb-alert"]]
  },
  {
    "id": "nr-build-topics",
    "type": "function",
    "name": "Build room topics",
    "func": "const bld = msg.buildingId;\nconst flr = msg.floorId;\nconst floors = (flr === '+') ?\n  ['f01','f02','f03','f04','f05','f06','f07','f08','f09','f10'] : [flr];\nconst out = [];\nfor (const f of floors) {\n  for (let r = 1; r <= 20; r++) {\n    const rid = 'r' + String(r).padStart(3,'0');\n    out.push({\n      topic: `campus/${bld}/${f}/cmd/${rid}`,\n      payload: JSON.stringify({ method:'applyConfig', params: msg.validData }),\n      qos: 1\n    });\n  }\n}\nreturn [out];",
    "outputs": 1,
    "x": 560,
    "y": 60,
    "wires": [["nr-mqtt-cmd-out"]]
  },
  {
    "id": "nr-mqtt-cmd-out",
    "type": "mqtt out",
    "name": "Push to rooms",
    "topic": "",
    "qos": "1",
    "retain": false,
    "broker": "nr-broker",
    "x": 760,
    "y": 60,
    "wires": []
  },
  {
    "id": "nr-tb-alert",
    "type": "function",
    "name": "Format TB alert",
    "func": "msg.url = global.get('TB_URL') + '/api/plugins/telemetry/DEVICE/' + (global.get('ALERT_DEVICE_ID') || 'unknown') + '/timeseries';\nmsg.headers = { 'X-Authorization': 'Bearer ' + global.get('TB_TOKEN'), 'Content-Type':'application/json' };\nmsg.method = 'POST';\nreturn msg;",
    "outputs": 1,
    "x": 560,
    "y": 120,
    "wires": [["nr-http-alert"]]
  },
  {
    "id": "nr-http-alert",
    "type": "http request",
    "name": "POST alert to TB",
    "method": "use",
    "ret": "txt",
    "x": 760,
    "y": 120,
    "wires": [[]]
  },
  {
    "id": "nr-heartbeat-in",
    "type": "mqtt in",
    "name": "Device heartbeat",
    "topic": "campus/+/+/+/telemetry",
    "qos": "0",
    "broker": "nr-broker",
    "x": 120,
    "y": 200,
    "wires": [["nr-parse-topic"]]
  },
  {
    "id": "nr-parse-topic",
    "type": "function",
    "name": "Parse topic & get desired",
    "func": "const parts = msg.topic.split('/');\nmsg.buildingId = parts[1];\nmsg.floorId    = parts[2];\nmsg.roomId     = parts[3];\nmsg.deviceKey  = `${parts[1]}-${parts[2]}-${parts[3]}`;\nlet reported;\ntry { reported = JSON.parse(msg.payload); } catch(e) { return null; }\nmsg.reported = reported;\nconst desired_hvac   = flow.get('desired_hvac_'   + msg.deviceKey);\nconst desired_dimmer = flow.get('desired_dimmer_' + msg.deviceKey);\nmsg.desired_hvac   = desired_hvac;\nmsg.desired_dimmer = desired_dimmer;\nconst hvac_diff   = desired_hvac   && desired_hvac   !== reported.hvac_mode;\nconst dimmer_diff = desired_dimmer && desired_dimmer !== reported.lighting_dimmer;\nif (hvac_diff || dimmer_diff) {\n  msg.needsSync = true;\n  msg.syncPayload = {};\n  if (hvac_diff)   msg.syncPayload.hvac_mode       = desired_hvac;\n  if (dimmer_diff) msg.syncPayload.lighting_dimmer  = desired_dimmer;\n  node.send([msg, null]);\n} else {\n  msg.needsSync = false;\n  node.send([null, msg]);\n}",
    "outputs": 2,
    "x": 340,
    "y": 200,
    "wires": [["nr-push-desired"], ["nr-mark-synced"]]
  },
  {
    "id": "nr-push-desired",
    "type": "function",
    "name": "Push desired state down",
    "func": "msg.topic   = `campus/cmd/${msg.deviceKey}`;\nmsg.payload = JSON.stringify({ method:'applyConfig', params: msg.syncPayload });\nreturn msg;",
    "outputs": 1,
    "x": 580,
    "y": 180,
    "wires": [["nr-cmd-out"]]
  },
  {
    "id": "nr-mark-synced",
    "type": "function",
    "name": "Update sync_status in TB",
    "func": "msg.payload = JSON.stringify({ sync_status:'OK', ts: Date.now() });\nmsg.topic   = 'v1/devices/me/telemetry';\nreturn msg;",
    "outputs": 1,
    "x": 580,
    "y": 220,
    "wires": [["nr-sync-out"]]
  },
  {
    "id": "nr-cmd-out",
    "type": "mqtt out",
    "name": "CMD out",
    "topic": "",
    "broker": "nr-broker",
    "x": 760,
    "y": 180,
    "wires": []
  },
  {
    "id": "nr-sync-out",
    "type": "mqtt out",
    "name": "Telemetry out",
    "topic": "",
    "broker": "nr-broker",
    "x": 760,
    "y": 220,
    "wires": []
  },
  {
    "id": "nr-tb-rpc-in",
    "type": "mqtt in",
    "name": "TB RPC requests",
    "topic": "v1/devices/+/rpc/request/+",
    "qos": "1",
    "broker": "nr-broker",
    "x": 120,
    "y": 320,
    "wires": [["nr-rpc-router"]]
  },
  {
    "id": "nr-rpc-router",
    "type": "function",
    "name": "Route RPC to device",
    "func": "const parts = msg.topic.split('/');\nconst deviceId  = parts[2];\nconst requestId = parts[5];\nlet rpc;\ntry { rpc = JSON.parse(msg.payload); } catch(e) { return null; }\nconst method = rpc.method;\nconst params = rpc.params;\nmsg.topic   = `campus/cmd/${deviceId}`;\nmsg.payload = JSON.stringify({ method, params, requestId });\nmsg.deviceId   = deviceId;\nmsg.requestId  = requestId;\nflow.set('pending_' + deviceId, { method, ts: Date.now() });\nreturn msg;",
    "outputs": 1,
    "x": 340,
    "y": 320,
    "wires": [["nr-device-cmd-out"]]
  },
  {
    "id": "nr-device-cmd-out",
    "type": "mqtt out",
    "name": "CMD to device",
    "topic": "",
    "qos": "1",
    "broker": "nr-broker",
    "x": 580,
    "y": 320,
    "wires": []
  },
  {
    "id": "nr-ack-in",
    "type": "mqtt in",
    "name": "Device ACK",
    "topic": "campus/+/+/ack/+",
    "qos": "0",
    "broker": "nr-broker",
    "x": 120,
    "y": 420,
    "wires": [["nr-clear-pending"]]
  },
  {
    "id": "nr-clear-pending",
    "type": "function",
    "name": "Clear pending state",
    "func": "const parts = msg.topic.split('/');\nconst roomId = `${parts[1]}-${parts[2]}-${parts[4]}`;\nflow.set('pending_' + roomId, null);\nmsg.topic   = 'v1/devices/me/telemetry';\nmsg.payload = JSON.stringify({ cmd_ack: true, room_id: roomId, ts: Date.now() });\nreturn msg;",
    "outputs": 1,
    "x": 340,
    "y": 420,
    "wires": [["nr-ack-out"]]
  },
  {
    "id": "nr-ack-out",
    "type": "mqtt out",
    "name": "ACK to TB",
    "topic": "",
    "broker": "nr-broker",
    "x": 580,
    "y": 420,
    "wires": []
  },
  {
    "id": "nr-telem-in",
    "type": "mqtt in",
    "name": "All rooms telemetry",
    "topic": "campus/+/+/+/telemetry",
    "qos": "0",
    "broker": "nr-broker",
    "x": 120,
    "y": 520,
    "wires": [["nr-enrich"]]
  },
  {
    "id": "nr-enrich",
    "type": "function",
    "name": "Enrich & forward to TB",
    "func": "const parts = msg.topic.split('/');\nconst building = parts[1];\nconst floor    = parts[2];\nconst room     = parts[3];\nlet data;\ntry { data = JSON.parse(msg.payload); } catch(e) { return null; }\ndata.building_id = building;\ndata.floor_id    = floor;\ndata.room_id     = room;\ndata.ts          = Date.now();\nmsg.payload = JSON.stringify(data);\nreturn msg;",
    "outputs": 1,
    "x": 340,
    "y": 520,
    "wires": [["nr-tb-telem-out"]]
  },
  {
    "id": "nr-tb-telem-out",
    "type": "mqtt out",
    "name": "Forward to TB broker",
    "topic": "v1/devices/me/telemetry",
    "broker": "nr-broker",
    "x": 580,
    "y": 520,
    "wires": []
  },
  {
    "id": "nr-broker",
    "type": "mqtt-broker",
    "name": "Local Mosquitto",
    "broker": "localhost",
    "port": "1883",
    "clientid": "node-red-phase3",
    "usetls": false,
    "compatmode": false,
    "keepalive": "60",
    "cleansession": true,
    "birthTopic": "",
    "birthQos": "0",
    "birthRetain": "false",
    "birthPayload": "",
    "closeTopic": "",
    "closeQos": "0",
    "closeRetain": "false",
    "closePayload": "",
    "willTopic": "",
    "willQos": "0",
    "willRetain": "false",
    "willPayload": ""
  }
]
